{
  "book_title": "Unearthed Arcana",
  "book_slug": "unearthed-arcana--90",
  "written": {
    "classes": 50,
    "feats": 95,
    "spells": 2
  },
  "skipped": {},
  "warnings": [
    "classes/Abjurer Variant: missing skillranks (no skill_ranks or skill_points parsed)",
    "classes/Abjurer Variant: missing classskills (FG will not auto-mark class skills at level 1)",
    "classes/Barbarian Variant: missing skillranks (no skill_ranks or skill_points parsed)",
    "classes/Barbarian Variant: missing classskills (FG will not auto-mark class skills at level 1)",
    "classes/Bard Variant: missing skillranks (no skill_ranks or skill_points parsed)",
    "classes/Bard Variant: missing classskills (FG will not auto-mark class skills at level 1)",
    "classes/Bardic Sage: unknown class skill name(s) for FG ruleset: engineering), royalty)",
    "classes/Battle Sorcerer: missing skillranks (no skill_ranks or skill_points parsed)",
    "classes/Cleric Variant: missing skillranks (no skill_ranks or skill_points parsed)",
    "classes/Cleric Variant: missing classskills (FG will not auto-mark class skills at level 1)",
    "classes/Cloistered Cleric: missing classskills (FG will not auto-mark class skills at level 1)",
    "classes/Conjurer Variant: missing skillranks (no skill_ranks or skill_points parsed)",
    "classes/Conjurer Variant: missing classskills (FG will not auto-mark class skills at level 1)",
    "classes/Divine Bard: missing skillranks (no skill_ranks or skill_points parsed)",
    "classes/Divine Bard: missing classskills (FG will not auto-mark class skills at level 1)",
    "classes/Diviner Variant: missing skillranks (no skill_ranks or skill_points parsed)",
    "classes/Diviner Variant: missing classskills (FG will not auto-mark class skills at level 1)",
    "classes/Domain Wizard: missing skillranks (no skill_ranks or skill_points parsed)",
    "classes/Domain Wizard: missing classskills (FG will not auto-mark class skills at level 1)",
    "classes/Druid Variant: missing skillranks (no skill_ranks or skill_points parsed)",
    "classes/Druid Variant: missing classskills (FG will not auto-mark class skills at level 1)",
    "classes/Druidic Avenger: missing skillranks (no skill_ranks or skill_points parsed)",
    "classes/Druidic Avenger: missing classskills (FG will not auto-mark class skills at level 1)",
    "classes/Enchanter Variant: missing skillranks (no skill_ranks or skill_points parsed)",
    "classes/Enchanter Variant: missing classskills (FG will not auto-mark class skills at level 1)",
    "classes/Evoker Variant: missing skillranks (no skill_ranks or skill_points parsed)",
    "classes/Evoker Variant: missing classskills (FG will not auto-mark class skills at level 1)",
    "classes/Expert: missing classskills (FG will not auto-mark class skills at level 1)",
    "classes/Fighter Variant: missing skillranks (no skill_ranks or skill_points parsed)",
    "classes/Fighter Variant: missing classskills (FG will not auto-mark class skills at level 1)",
    "classes/Illusionist Variant: missing skillranks (no skill_ranks or skill_points parsed)",
    "classes/Illusionist Variant: missing classskills (FG will not auto-mark class skills at level 1)",
    "classes/Monk Variant: missing skillranks (no skill_ranks or skill_points parsed)",
    "classes/Monk Variant: missing classskills (FG will not auto-mark class skills at level 1)",
    "classes/Monk Variant: Fighting Styles: missing skillranks (no skill_ranks or skill_points parsed)",
    "classes/Monk Variant: Fighting Styles: missing classskills (FG will not auto-mark class skills at level 1)",
    "classes/Necromancer Variant: missing skillranks (no skill_ranks or skill_points parsed)",
    "classes/Necromancer Variant: missing classskills (FG will not auto-mark class skills at level 1)",
    "classes/Paladin of Freedom: missing skillranks (no skill_ranks or skill_points parsed)",
    "classes/Paladin of Freedom: missing classskills (FG will not auto-mark class skills at level 1)",
    "classes/Paladin of Slaughter: missing skillranks (no skill_ranks or skill_points parsed)",
    "classes/Paladin of Slaughter: missing classskills (FG will not auto-mark class skills at level 1)",
    "classes/Paladin of Tyranny: missing skillranks (no skill_ranks or skill_points parsed)",
    "classes/Paladin of Tyranny: missing classskills (FG will not auto-mark class skills at level 1)",
    "classes/Paladin Variant: missing skillranks (no skill_ranks or skill_points parsed)",
    "classes/Paladin Variant: missing classskills (FG will not auto-mark class skills at level 1)",
    "classes/Planar Ranger: missing skillranks (no skill_ranks or skill_points parsed)",
    "classes/Planar Ranger: missing classskills (FG will not auto-mark class skills at level 1)",
    "classes/Prestige Paladin: unknown class skill name(s) for FG ruleset: royalty)",
    "classes/Ranger Variant: missing skillranks (no skill_ranks or skill_points parsed)",
    "classes/Ranger Variant: missing classskills (FG will not auto-mark class skills at level 1)",
    "classes/Rogue Variant: missing skillranks (no skill_ranks or skill_points parsed)",
    "classes/Rogue Variant: missing classskills (FG will not auto-mark class skills at level 1)",
    "classes/Savage Bard: missing skillranks (no skill_ranks or skill_points parsed)",
    "classes/Savage Bard: missing classskills (FG will not auto-mark class skills at level 1)",
    "classes/Sorcerer/Wizard Variant: missing skillranks (no skill_ranks or skill_points parsed)",
    "classes/Sorcerer/Wizard Variant: missing classskills (FG will not auto-mark class skills at level 1)",
    "classes/Totem Barbarian: missing skillranks (no skill_ranks or skill_points parsed)",
    "classes/Totem Barbarian: missing classskills (FG will not auto-mark class skills at level 1)",
    "classes: no classfeatures parsed for Totem Barbarian",
    "classes/Transmuter Variant: missing skillranks (no skill_ranks or skill_points parsed)",
    "classes/Transmuter Variant: missing classskills (FG will not auto-mark class skills at level 1)",
    "classes/Urban Ranger: missing skillranks (no skill_ranks or skill_points parsed)",
    "classes/Warrior: missing classskills (FG will not auto-mark class skills at level 1)",
    "classes/Wilderness Rogue: missing skillranks (no skill_ranks or skill_points parsed)",
    "classes/Wilderness Rogue: missing classskills (FG will not auto-mark class skills at level 1)",
    "classes/Wizard Variant: missing skillranks (no skill_ranks or skill_points parsed)",
    "classes/Wizard Variant: missing classskills (FG will not auto-mark class skills at level 1)"
  ],
  "total_written": 147,
  "total_skipped": 0
}